jwst_coronagraph_visibility/__init__.py
jwst_coronagraph_visibility/gui.py
jwst_coronagraph_visibility/skyvec2ins.py
jwst_coronagraph_visibility/tests/__init__.py
jwst_coronagraph_visibility/tests/test_gui.py
jwst_coronagraph_visibility/tests/test_skyvec2ins.py
jwst_coronagraph_visibility/tests/targets/1RXSJ160929p1-210524/c1_x.csv
jwst_coronagraph_visibility/tests/targets/1RXSJ160929p1-210524/c1_y.csv
jwst_coronagraph_visibility/tests/targets/1RXSJ160929p1-210524/c2_x.csv
jwst_coronagraph_visibility/tests/targets/1RXSJ160929p1-210524/c2_y.csv
jwst_coronagraph_visibility/tests/targets/1RXSJ160929p1-210524/c3_x.csv
jwst_coronagraph_visibility/tests/targets/1RXSJ160929p1-210524/c3_y.csv
jwst_coronagraph_visibility/tests/targets/1RXSJ160929p1-210524/e_x.csv
jwst_coronagraph_visibility/tests/targets/1RXSJ160929p1-210524/e_y.csv
jwst_coronagraph_visibility/tests/targets/1RXSJ160929p1-210524/elongation_rad.csv
jwst_coronagraph_visibility/tests/targets/1RXSJ160929p1-210524/input.txt
jwst_coronagraph_visibility/tests/targets/1RXSJ160929p1-210524/n_x.csv
jwst_coronagraph_visibility/tests/targets/1RXSJ160929p1-210524/n_y.csv
jwst_coronagraph_visibility/tests/targets/1RXSJ160929p1-210524/observable.csv
jwst_coronagraph_visibility/tests/targets/1RXSJ160929p1-210524/roll_rad.csv
jwst_coronagraph_visibility/tests/targets/1RXSJ160929p1-210524/x.csv
jwst_coronagraph_visibility/tests/targets/Fomalhaut/c1_x.csv
jwst_coronagraph_visibility/tests/targets/Fomalhaut/c1_y.csv
jwst_coronagraph_visibility/tests/targets/Fomalhaut/c2_x.csv
jwst_coronagraph_visibility/tests/targets/Fomalhaut/c2_y.csv
jwst_coronagraph_visibility/tests/targets/Fomalhaut/c3_x.csv
jwst_coronagraph_visibility/tests/targets/Fomalhaut/c3_y.csv
jwst_coronagraph_visibility/tests/targets/Fomalhaut/e_x.csv
jwst_coronagraph_visibility/tests/targets/Fomalhaut/e_y.csv
jwst_coronagraph_visibility/tests/targets/Fomalhaut/elongation_rad.csv
jwst_coronagraph_visibility/tests/targets/Fomalhaut/input.txt
jwst_coronagraph_visibility-0.5.0.dist-info/LICENSE
jwst_coronagraph_visibility-0.5.0.dist-info/METADATA
jwst_coronagraph_visibility-0.5.0.dist-info/WHEEL
jwst_coronagraph_visibility-0.5.0.dist-info/entry_points.txt
jwst_coronagraph_visibility-0.5.0.dist-info/top_level.txt
jwst_coronagraph_visibility-0.5.0.dist-info/RECORD
