Metadata-Version: 2.1
Name: jwst-coronagraph-visibility
Version: 0.5.0
Summary: JWST coronagraphic target observability calculator
Home-page: https://github.com/spacetelescope/jwst_coronagraph_visibility
Author: Space Telescope Science Institute
License: MIT
Keywords: jwst astro astronomy observation coronagraph
Classifier: Development Status :: 3 - Alpha
Classifier: License :: OSI Approved :: MIT License
Classifier: Programming Language :: Python :: 3.8
License-File: LICENSE
Requires-Dist: numpy (>=1.17.5)
Requires-Dist: matplotlib (>=3.1.3)
Requires-Dist: requests (>=2.8.1)
Requires-Dist: pysiaf (>=0.7.1)
Provides-Extra: dev
Requires-Dist: pytest (>=2.9.1) ; extra == 'dev'
Requires-Dist: lxml (>=3.5.0) ; extra == 'dev'
Requires-Dist: check-manifest (>=0.31) ; extra == 'dev'
